lilliepy_rebound/__init__.py
lilliepy_rebound/rebound.py
lilliepy_rebound-0.0.1.dist-info/METADATA
lilliepy_rebound-0.0.1.dist-info/WHEEL
lilliepy_rebound-0.0.1.dist-info/top_level.txt
lilliepy_rebound-0.0.1.dist-info/RECORD
